<?xml version="1.0" encoding="UTF-8"?>
<!DOCTYPE tiles-definitions 
   PUBLIC "-//Apache Software Foundation//DTD Tiles Configuration 3.0//EN" "http://tiles.apache.org/dtds/tiles-config_3_0.dtd">
<tiles-definitions>
	<!-- 인덱스는 히든 (인덱스에서는 사이드바를 안불러옴 -->
	<definition name="t_index" template="/WEB-INF/view/index.jsp">
	</definition>
	<!-- 메인페이지는 인덱스를 상속받아서 생성 (사이드바 삽입용) -->
	<!-- welcome page -->
	<definition name="t_main0" extends="t_index">
		<put-attribute name="title" value="찰리" />
		<put-attribute name="side" value="/WEB-INF/view/side0.jsp" />
		<put-attribute name="main" value="/WEB-INF/view/side0.jsp" />
	</definition>
	<!-- 항목 페이지 -->
	<definition name="t_main1" extends="t_index">
		<put-attribute name="side" value="/WEB-INF/view/side1.jsp" />
	</definition>
	<definition name="t_main2" extends="t_index">
		<put-attribute name="side" value="/WEB-INF/view/side2.jsp" />
	</definition>
	<definition name="t_main3" extends="t_index">
		<put-attribute name="side" value="/WEB-INF/view/side3.jsp" />
	</definition>
	<definition name="t_main4" extends="t_index">
		<put-attribute name="side" value="/WEB-INF/view/side4.jsp" />
	</definition>
	<definition name="t_main5" extends="t_index">
		<put-attribute name="side" value="/WEB-INF/view/side5.jsp" />
	</definition>
	<definition name="t_main6" extends="t_index">
		<put-attribute name="side" value="/WEB-INF/view/side6.jsp" />
	</definition>
	<!-- 항목의 목차 페이지들 -->
	<definition name="t_menu1-1" extends="t_main1">
		<put-attribute name="title" value="menu1-1" />
		<put-attribute name="main" value="/WEB-INF/view/view1-1.jsp" />
	</definition>
	<definition name="t_menu1-2" extends="t_main1">
		<put-attribute name="title" value="menu1-2" />
		<put-attribute name="main" value="/WEB-INF/view/view1-2.jsp" />
	</definition>
	<definition name="t_menu1-3" extends="t_main1">
		<put-attribute name="title" value="menu1-3" />
		<put-attribute name="main" value="/WEB-INF/view/view1-3.jsp" />
	</definition>
	<definition name="t_menu1-4" extends="t_main1">
		<put-attribute name="title" value="menu1-4" />
		<put-attribute name="main" value="/WEB-INF/view/view1-4.jsp" />
	</definition>
	<definition name="t_menu1-5" extends="t_main1">
		<put-attribute name="title" value="menu1-5" />
		<put-attribute name="main" value="/WEB-INF/view/view1-5.jsp" />
	</definition>
	<definition name="t_menu2-1" extends="t_main2">
		<put-attribute name="title" value="menu2-1" />
		<put-attribute name="main" value="/WEB-INF/view/view2-1.jsp" />
	</definition>
	<definition name="t_menu2-2" extends="t_main2">
		<put-attribute name="title" value="menu2-2" />
		<put-attribute name="main" value="/WEB-INF/view/view2-2.jsp" />
	</definition>
	<definition name="t_menu2-3" extends="t_main2">
		<put-attribute name="title" value="menu2-3" />
		<put-attribute name="main" value="/WEB-INF/view/view2-3.jsp" />
	</definition>
	<definition name="t_menu2-4" extends="t_main2">
		<put-attribute name="title" value="menu2-4" />
		<put-attribute name="main" value="/WEB-INF/view/view2-4.jsp" />
	</definition>
	<definition name="t_menu2-5" extends="t_main2">
		<put-attribute name="title" value="menu2-5" />
		<put-attribute name="main" value="/WEB-INF/view/view2-5.jsp" />
	</definition>
	<definition name="contentIndex" extends="t_main3">
		<put-attribute name="title" value="menu3-1" />
		<put-attribute name="main" value="/WEB-INF/view/contentIndex.jsp" />
	</definition>
	<definition name="contentWrite" extends="t_main3">
		<put-attribute name="title" value="menu3-1" />
		<put-attribute name="main" value="/WEB-INF/view/contentWrite.jsp" />
	</definition>
	<definition name="contentView" extends="t_main3">
		<put-attribute name="title" value="menu3-1" />
		<put-attribute name="main" value="/WEB-INF/view/contentView.jsp" />
	</definition>
	<definition name="contentModify" extends="t_main3">
		<put-attribute name="title" value="menu3-1" />
		<put-attribute name="main" value="/WEB-INF/view/contentModify.jsp" />
	</definition>
	<definition name="chatView" extends="t_main3">
		<put-attribute name="title" value="menu3-2" />
		<put-attribute name="main" value="/WEB-INF/view/chatView.jsp" />
	</definition>
	<definition name="t_menu3-3" extends="t_main3">
		<put-attribute name="title" value="menu3-3" />
		<put-attribute name="main" value="/WEB-INF/view/view3-3.jsp" />
	</definition>
	<definition name="t_menu3-4" extends="t_main3">
		<put-attribute name="title" value="menu3-4" />
		<put-attribute name="main" value="/WEB-INF/view/view3-4.jsp" />
	</definition>
	<definition name="t_menu3-5" extends="t_main3">
		<put-attribute name="title" value="menu3-5" />
		<put-attribute name="main" value="/WEB-INF/view/view3-5.jsp" />
	</definition>
	<definition name="t_menu4-1" extends="t_main4">
		<put-attribute name="title" value="menu4-1" />
		<put-attribute name="main" value="/WEB-INF/view/view4-1.jsp" />
	</definition>
	<definition name="t_menu4-2" extends="t_main4">
		<put-attribute name="title" value="menu4-2" />
		<put-attribute name="main" value="/WEB-INF/view/view4-2.jsp" />
	</definition>
	<definition name="t_menu4-3" extends="t_main4">
		<put-attribute name="title" value="menu4-3" />
		<put-attribute name="main" value="/WEB-INF/view/view4-3.jsp" />
	</definition>
	<definition name="t_menu4-4" extends="t_main4">
		<put-attribute name="title" value="menu4-4" />
		<put-attribute name="main" value="/WEB-INF/view/view4-4.jsp" />
	</definition>
	<definition name="t_menu4-5" extends="t_main4">
		<put-attribute name="title" value="menu4-5" />
		<put-attribute name="main" value="/WEB-INF/view/view4-5.jsp" />
	</definition>
	<definition name="t_menu5-1" extends="t_main5">
		<put-attribute name="title" value="menu5-1" />
		<put-attribute name="main" value="/WEB-INF/view/view5-1.jsp" />
	</definition>
	<definition name="t_menu5-2" extends="t_main5">
		<put-attribute name="title" value="menu5-2" />
		<put-attribute name="main" value="/WEB-INF/view/view5-2.jsp" />
	</definition>
	<definition name="t_menu5-3" extends="t_main5">
		<put-attribute name="title" value="menu5-3" />
		<put-attribute name="main" value="/WEB-INF/view/view5-3.jsp" />
	</definition>
	<definition name="t_menu5-4" extends="t_main5">
		<put-attribute name="title" value="menu5-4" />
		<put-attribute name="main" value="/WEB-INF/view/view5-4.jsp" />
	</definition>
	<definition name="t_menu5-5" extends="t_main5">
		<put-attribute name="title" value="menu5-5" />
		<put-attribute name="main" value="/WEB-INF/view/view5-5.jsp" />
	</definition>
	<definition name="t_menu6-1" extends="t_main6">
		<put-attribute name="title" value="menu6-1" />
		<put-attribute name="main" value="/WEB-INF/view/view6-1.jsp" />
	</definition>
	<definition name="t_menu6-2" extends="t_main6">
		<put-attribute name="title" value="menu6-2" />
		<put-attribute name="main" value="/WEB-INF/view/view6-2.jsp" />
	</definition>
	<definition name="t_menu6-3" extends="t_main6">
		<put-attribute name="title" value="menu6-3" />
		<put-attribute name="main" value="/WEB-INF/view/view6-3.jsp" />
	</definition>
	<definition name="t_menu6-4" extends="t_main6">
		<put-attribute name="title" value="menu6-4" />
		<put-attribute name="main" value="/WEB-INF/view/view6-4.jsp" />
	</definition>
	<definition name="t_menu6-5" extends="t_main6">
		<put-attribute name="title" value="menu6-5" />
		<put-attribute name="main" value="/WEB-INF/view/view6-5.jsp" />
	</definition>
	<!-- <definition name="t_el" extends="t_default"> 
				<put-attribute name="main" expression="/WEB-INF/view/${main}" /> 
		</definition> 
		<definition name="t_el_title" extends="t_default"> 
			<put-attribute name="title" expression="${title}" /> 
			<put-attribute name="main" expression="/WEB-INF/view/${main}" /> 
		</definition> -->
</tiles-definitions>